{
    "67bed8d149612332d689360a": {
        "1742832438.6420577": [
            {
                "object": "",
                "action": "idle",
                "robot_interaction": false,
                "on": ""
            }
        ],
        "1742832475.0143774": [
            {
                "object": "object_3",
                "action": "grasp",
                "robot_interaction": false,
                "on": ""
            }
        ],
        "1742832476.0144968": [
            {
                "object": "object_3",
                "action": "place_down",
                "robot_interaction": false,
                "on": "object_6"
            }
        ],
        "1742832478.4155788": [
            {
                "object": "",
                "action": "idle",
                "robot_interaction": false,
                "on": ""
            }
        ],
        "1742832480.2123525": [
            {
                "object": "object_5",
                "action": "grasp",
                "robot_interaction": false,
                "on": ""
            }
        ],
        "1742832482.1340325": [
            {
                "object": "object_5",
                "action": "place_down",
                "robot_interaction": false,
                "on": "object_6"
            }
        ],
        "1742832483.7345538": [
            {
                "object": "",
                "action": "idle",
                "robot_interaction": false,
                "on": ""
            }
        ]
    },
    "67bed8e949612332d6893630": {
        "1742832438.6420577": [
            {
                "object": "",
                "action": "idle",
                "robot_interaction": false,
                "on": ""
            }
        ],
        "1742832475.0143774": [
            {
                "object": "object_1",
                "action": "grasp",
                "robot_interaction": false,
                "on": ""
            }
        ],
        "1742832476.0144968": [
            {
                "object": "object_1",
                "action": "place_down",
                "robot_interaction": false,
                "on": "object_4"
            }
        ],
        "1742832478.4155788": [
            {
                "object": "",
                "action": "idle",
                "robot_interaction": false,
                "on": ""
            }
        ],
        "1742832482.1340325": [
            {
                "object": "object_2",
                "action": "grasp",
                "robot_interaction": false,
                "on": ""
            }
        ],
        "1742832483.7345538": [
            {
                "object": "object_2",
                "action": "place_down",
                "robot_interaction": false,
                "on": "object_4"
            }
        ],
        "1742832489.141047": [
            {
                "object": "",
                "action": "idle",
                "robot_interaction": false,
                "on": ""
            }
        ]
    }
}